jusho/__init__.py
jusho/async_client.py
jusho/client.py
jusho/errors.py
jusho/models.py
jusho/py.typed
normal_jusho-0.2.0.dist-info/METADATA
normal_jusho-0.2.0.dist-info/WHEEL
normal_jusho-0.2.0.dist-info/licenses/LICENSE
normal_jusho-0.2.0.dist-info/RECORD
