Metadata-Version: 2.4
Name: normal-jusho
Version: 0.2.0
Summary: Python SDK for the Jusho Japanese address normalization API
Project-URL: Homepage, https://jusho.dev
Project-URL: Documentation, https://jusho.dev/docs
Project-URL: Repository, https://github.com/1000ri-jp/normal-jusho
Project-URL: Bug Tracker, https://github.com/1000ri-jp/normal-jusho/issues
Project-URL: API, https://api.jusho.dev
Author-email: Jusho <info@jusho.dev>
License-Expression: MIT
License-File: LICENSE
Keywords: address,geocoding,japan,japanese,normalization,postal-code,zipcode
Classifier: Development Status :: 4 - Beta
Classifier: Intended Audience :: Developers
Classifier: License :: OSI Approved :: MIT License
Classifier: Operating System :: OS Independent
Classifier: Programming Language :: Python :: 3
Classifier: Programming Language :: Python :: 3.9
Classifier: Programming Language :: Python :: 3.10
Classifier: Programming Language :: Python :: 3.11
Classifier: Programming Language :: Python :: 3.12
Classifier: Programming Language :: Python :: 3.13
Classifier: Topic :: Software Development :: Libraries :: Python Modules
Classifier: Topic :: Text Processing
Classifier: Typing :: Typed
Requires-Python: >=3.9
Requires-Dist: httpx>=0.24.0
